prompeter/__init__.py
prompeter/prompts.py
prompeter-0.0.3.dist-info/METADATA
prompeter-0.0.3.dist-info/WHEEL
prompeter-0.0.3.dist-info/licenses/LICENSE
prompeter-0.0.3.dist-info/RECORD
