Metadata-Version: 2.3
Name: prompeter
Version: 0.0.3
Summary: Prompeter defines a data model for structuring prompts for LLMs and loads yaml and json files following this model
Project-URL: Homepage, https://github.com/itk-ai/prompeter
Project-URL: Issues, https://github.com/itk-ai/prompeter/issues
Author-email: Daniel Kjeldsmark Andreasen <akda@aarhus.dk>
Classifier: License :: OSI Approved :: European Union Public Licence 1.2 (EUPL 1.2)
Classifier: Operating System :: OS Independent
Classifier: Programming Language :: Python :: 3
Requires-Python: >=3.9
Requires-Dist: markdown-strings
Requires-Dist: pydantic>=2
Requires-Dist: ruamel-yaml
